{"create_time": 0.819426, "error": null, "issues": [], "success": true, "sym_cnt": 1, "sym_time": 13.831797, "time": 13.850979, "total_info": {"caller2cnt": {"ether_thief": 3, "get_transaction_sequence": 14, "integer": 9, "is_possible": 33, "mutation_pruner": 2, "state_cahnge_exernal_calls1": 3, "state_cahnge_exernal_calls2": 3}, "caller2time": {"ether_thief": 0.005666000000000001, "get_transaction_sequence": 2.760636, "integer": 0.044684999999999996, "is_possible": 3.409556999999999, "mutation_pruner": 0.002436, "state_cahnge_exernal_calls1": 0.6291549999999999, "state_cahnge_exernal_calls2": 0.693039}}, "total_states": 747}