{"create_time": 1.345161, "error": null, "issues": [], "success": true, "sym_cnt": 1, "sym_time": 14.261333, "time": 14.279327, "total_info": {"caller2cnt": {"ether_thief": 4, "get_transaction_sequence": 18, "integer": 6, "is_possible": 42, "mutation_pruner": 27, "state_cahnge_exernal_calls1": 4}, "caller2time": {"ether_thief": 0.230663, "get_transaction_sequence": 0.691971, "integer": 0.250874, "is_possible": 1.2335120000000002, "mutation_pruner": 0.8765000000000001, "state_cahnge_exernal_calls1": 0.24672}}, "total_states": 1738}