{"create_time": 1.622639, "error": null, "issues": [], "success": true, "sym_cnt": 1, "sym_time": 161.632512, "time": 161.650789, "total_info": {"caller2cnt": {"ether_thief": 77, "get_transaction_sequence": 322, "integer": 239, "is_possible": 211, "mutation_pruner": 128, "state_cahnge_exernal_calls1": 77, "state_cahnge_exernal_calls2": 6, "state_cahnge_exernal_calls3": 5}, "caller2time": {"ether_thief": 7.895911000000003, "get_transaction_sequence": 25.201144000000006, "integer": 10.968550999999998, "is_possible": 18.90470000000001, "mutation_pruner": 9.142119, "state_cahnge_exernal_calls1": 7.917897000000002, "state_cahnge_exernal_calls2": 0.073785, "state_cahnge_exernal_calls3": 0.533207}}, "total_states": 15674}