{"create_time": 1.28951, "error": null, "issues": [], "success": true, "sym_cnt": 1, "sym_time": 4.375053, "time": 4.392614, "total_info": {"caller2cnt": {"ether_thief": 3, "get_transaction_sequence": 8, "integer": 2, "is_possible": 43, "mutation_pruner": 12, "state_cahnge_exernal_calls1": 3, "state_cahnge_exernal_calls3": 2}, "caller2time": {"ether_thief": 0.02319, "get_transaction_sequence": 0.098606, "integer": 0.000855, "is_possible": 0.49654099999999995, "mutation_pruner": 0.15352, "state_cahnge_exernal_calls1": 0.044105, "state_cahnge_exernal_calls3": 0.027603000000000003}}, "total_states": 541}