{"create_time": 0.716036, "error": null, "issues": [], "success": true, "sym_cnt": 1, "sym_time": 4.198269, "time": 4.216139, "total_info": {"caller2cnt": {"ether_thief": 3, "get_transaction_sequence": 5, "is_possible": 28, "mutation_pruner": 1, "state_cahnge_exernal_calls1": 3, "state_cahnge_exernal_calls2": 2}, "caller2time": {"ether_thief": 0.017065999999999998, "get_transaction_sequence": 0.14881899999999998, "is_possible": 0.3577639999999999, "mutation_pruner": 0.005146, "state_cahnge_exernal_calls1": 0.065247, "state_cahnge_exernal_calls2": 0.034864}}, "total_states": 574}