{"create_time": 1.042768, "error": null, "issues": [], "success": true, "sym_cnt": 1, "sym_time": 3.990769, "time": 4.008468, "total_info": {"caller2cnt": {"ether_thief": 1, "get_transaction_sequence": 3, "integer": 2, "is_possible": 35, "mutation_pruner": 6, "state_cahnge_exernal_calls1": 1, "state_cahnge_exernal_calls3": 1}, "caller2time": {"ether_thief": 0.000829, "get_transaction_sequence": 0.025971, "integer": 0.000852, "is_possible": 0.46460799999999997, "mutation_pruner": 0.063039, "state_cahnge_exernal_calls1": 0.020749, "state_cahnge_exernal_calls3": 0.013606}}, "total_states": 426}