{"create_time": 1.671776, "error": null, "issues": [], "success": true, "sym_cnt": 1, "sym_time": 41.024036, "time": 41.042878, "total_info": {"caller2cnt": {"ether_thief": 12, "get_transaction_sequence": 44, "integer": 42, "is_possible": 228, "mutation_pruner": 28, "state_cahnge_exernal_calls1": 12, "state_cahnge_exernal_calls2": 6, "state_cahnge_exernal_calls3": 1}, "caller2time": {"ether_thief": 0.887166, "get_transaction_sequence": 2.3021849999999997, "integer": 0.8617420000000001, "is_possible": 13.974089000000003, "mutation_pruner": 0.888949, "state_cahnge_exernal_calls1": 0.879697, "state_cahnge_exernal_calls2": 0.28112, "state_cahnge_exernal_calls3": 0.050643}}, "total_states": 3754}